wwpdb/utils/message_queue/DetachedMessageConsumerExample.py
wwpdb/utils/message_queue/MessageConsumerBase.py
wwpdb/utils/message_queue/MessagePublisher.py
wwpdb/utils/message_queue/MessageQueueConnection.py
wwpdb/utils/message_queue/MessageSubscriberBase.py
wwpdb/utils/message_queue/__init__.py
wwpdb_utils_message_queue-0.7.dist-info/METADATA
wwpdb_utils_message_queue-0.7.dist-info/WHEEL
wwpdb_utils_message_queue-0.7.dist-info/RECORD
